pygali/__init__.py
pygali/date_utils.py
PyGaLiTool-0.0.6.dist-info/LICENSE
PyGaLiTool-0.0.6.dist-info/METADATA
PyGaLiTool-0.0.6.dist-info/WHEEL
PyGaLiTool-0.0.6.dist-info/top_level.txt
PyGaLiTool-0.0.6.dist-info/RECORD
