Metadata-Version: 2.1
Name: PyGaLiTool
Version: 0.0.6
Summary: Common Tools
Home-page: https://github.com/xuranyang/PyGaLiTool
Author: xuranyang
Author-email: xuranyang96@gmail.com
License: Apache
Keywords: tool
Platform: UNKNOWN
Classifier: Operating System :: OS Independent
Classifier: Intended Audience :: Developers
Classifier: License :: OSI Approved :: MIT License
Classifier: Programming Language :: Python :: 3
Requires-Python: >=3.8
Requires-Dist: pytz (>=2021.1)
